FileSystemModel/__init__.py
FileSystemModel/_dir.py
FileSystemModel/_file.py
FileSystemModel/_path.py
FileSystemModel-1.0.0.dist-info/LICENSE
FileSystemModel-1.0.0.dist-info/METADATA
FileSystemModel-1.0.0.dist-info/WHEEL
FileSystemModel-1.0.0.dist-info/top_level.txt
FileSystemModel-1.0.0.dist-info/RECORD
