Metadata-Version: 2.1
Name: FileSystemModel
Version: 1.0.0
Summary: A user-friendly file system model.
Author-email: 张恒华 <1652709417@qq.com>
Classifier: Programming Language :: Python :: 3
Classifier: License :: OSI Approved :: MIT License
Classifier: Operating System :: Microsoft :: Windows
License-File: LICENSE
Requires-Dist: pywin32
Requires-Dist: prettytable
